universal_parser/__init__.py
universal_parser/main.py
universal_parser/object_converter.py
universal_parser/serializer_factory.py
universal_parser/student.py
universal_parser/logger/__init__.py
universal_parser/logger/logger.py
universal_parser/serializers/__init__.py
universal_parser/serializers/json_serializer/__init__.py
universal_parser/serializers/json_serializer/json_serializer.py
universal_parser/serializers/pickle_serializer/__init__.py
universal_parser/serializers/pickle_serializer/pickle_serializer.py
universal_parser/serializers/toml_serializer/__init__.py
universal_parser/serializers/toml_serializer/toml_serializer.py
universal_parser/serializers/yaml_serializer/__init__.py
universal_parser/serializers/yaml_serializer/yaml_serializer.py
universal_parser-1.0.9.dist-info/LICENSE
universal_parser-1.0.9.dist-info/METADATA
universal_parser-1.0.9.dist-info/WHEEL
universal_parser-1.0.9.dist-info/entry_points.txt
universal_parser-1.0.9.dist-info/top_level.txt
universal_parser-1.0.9.dist-info/RECORD
